packetmq/__init__.py
packetmq/packet.py
packetmq/packetprotocol.py
packetmq-0.1.6a1.data/data/README.md
packetmq-0.1.6a1.data/data/pypi.rst
packetmq-0.1.6a1.data/data/requirements.txt
packetmq-0.1.6a1.dist-info/DESCRIPTION.rst
packetmq-0.1.6a1.dist-info/METADATA
packetmq-0.1.6a1.dist-info/RECORD
packetmq-0.1.6a1.dist-info/WHEEL
packetmq-0.1.6a1.dist-info/metadata.json
packetmq-0.1.6a1.dist-info/top_level.txt
