Metadata-Version: 2.0
Name: packetmq
Version: 0.1.6a1
Summary: Packet based networking
Home-page: http://packetmq.readthedocs.org/en/latest/
Author: notna
Author-email: notna@apparat.org
License: UNKNOWN
Keywords: bidict,packet,packetmq,twisted,tcp,socket,network
Platform: UNKNOWN
Classifier: Development Status :: 4 - Beta
Classifier: Framework :: Twisted
Classifier: Intended Audience :: Developers
Classifier: Intended Audience :: Information Technology
Classifier: Intended Audience :: Telecommunications Industry
Classifier: License :: OSI Approved
Classifier: License :: OSI Approved :: GNU General Public License v2 or later (GPLv2+)
Classifier: Natural Language :: English
Classifier: Operating System :: OS Independent
Classifier: Programming Language :: Python
Classifier: Programming Language :: Python :: 2
Classifier: Programming Language :: Python :: 2.7
Classifier: Topic :: Communications
Classifier: Topic :: Internet
Classifier: Topic :: Software Development
Classifier: Topic :: Software Development :: Libraries
Classifier: Topic :: Software Development :: Libraries :: Python Modules
Requires: twisted
Requires: msgpack
Requires: bidict
Provides: packetmq
